windborne/__init__.py
windborne/api_request.py
windborne/cli.py
windborne/forecasts_api.py
windborne/observation_formatting.py
windborne/observations_api.py
windborne/track_formatting.py
windborne/utils.py
windborne-1.4.3.dist-info/METADATA
windborne-1.4.3.dist-info/WHEEL
windborne-1.4.3.dist-info/entry_points.txt
windborne-1.4.3.dist-info/top_level.txt
windborne-1.4.3.dist-info/RECORD
