Metadata-Version: 2.4
Name: windborne
Version: 1.4.3
Summary: A Python library for interacting with WindBorne Data and Forecasts API
Author-email: WindBorne Systems <data@windbornesystems.com>
Classifier: Programming Language :: Python :: 3
Classifier: License :: OSI Approved :: MIT License
Requires-Python: >=3.6
Requires-Dist: requests
Requires-Dist: PyJWT
Requires-Dist: numpy
Requires-Dist: xarray
Requires-Dist: pandas
Requires-Dist: netCDF4
